osc/OscConfigParser.py
osc/__init__.py
osc/babysitter.py
osc/build.py
osc/checker.py
osc/cmdln.py
osc/commandline.py
osc/commandline_common.py
osc/commandline_git.py
osc/conf.py
osc/connection.py
osc/core.py
osc/credentials.py
osc/fetch.py
osc/grabber.py
osc/meter.py
osc/oscerr.py
osc/oscssl.py
osc/py.typed
osc/store.py
osc/_private/__init__.py
osc/_private/api.py
osc/_private/api_build.py
osc/_private/api_configuration.py
osc/_private/api_source.py
osc/_private/common.py
osc/_private/package.py
osc/_private/request.py
osc/commands/__init__.py
osc/commands/fork.py
osc/commands/person.py
osc/commands/person_register.py
osc/commands/person_search.py
osc/commands/repo.py
osc/commands/repo_add.py
osc/commands/repo_list.py
osc/commands/repo_remove.py
osc/commands/rmkpac.py
osc/commands_git/__init__.py
osc/commands_git/api.py
osc/commands_git/login.py
osc/commands_git/login_add.py
osc/commands_git/login_gitcredentials_helper.py
osc/commands_git/login_list.py
osc/commands_git/login_remove.py
osc/commands_git/login_update.py
osc/commands_git/meta.py
osc/commands_git/meta_info.py
osc/commands_git/meta_list.py
osc/commands_git/meta_pull.py
osc/commands_git/meta_reset.py
osc/commands_git/meta_set.py
osc/commands_git/pr.py
osc/commands_git/pr_cancel_scheduled_merge.py
osc/commands_git/pr_checkout.py
osc/commands_git/pr_close.py
osc/commands_git/pr_comment.py
osc/commands_git/pr_create.py
osc/commands_git/pr_dump.py
osc/commands_git/pr_get.py
osc/commands_git/pr_list.py
osc/commands_git/pr_merge.py
osc/commands_git/pr_reopen.py
osc/commands_git/pr_review.py
osc/commands_git/pr_review_approve.py
osc/commands_git/pr_review_decline.py
osc/commands_git/pr_review_interactive.py
osc/commands_git/pr_search.py
osc/commands_git/pr_set.py
osc/commands_git/pr_show_patch.py
osc/commands_git/repo.py
osc/commands_git/repo_clone.py
osc/commands_git/repo_fork.py
osc/commands_git/repo_list.py
osc/commands_git/ssh_key.py
osc/commands_git/ssh_key_add.py
osc/commands_git/ssh_key_list.py
osc-1.23.0.dist-info/licenses/AUTHORS
osc-1.23.0.dist-info/licenses/COPYING
osc-1.23.0.dist-info/METADATA
osc-1.23.0.dist-info/WHEEL
osc-1.23.0.dist-info/entry_points.txt
osc-1.23.0.dist-info/top_level.txt
osc-1.23.0.dist-info/RECORD
