Metadata-Version: 2.4
Name: osc
Version: 1.23.0
Summary: openSUSE commander
Home-page: http://en.opensuse.org/openSUSE:OSC
Download-URL: https://github.com/openSUSE/osc
Author: openSUSE project
Author-email: opensuse-buildservice@opensuse.org
License: GPLv2+
Keywords: openSUSE,SUSE,RPM,build,buildservice,command-line
Classifier: Development Status :: 5 - Production/Stable
Classifier: Environment :: Console
Classifier: Intended Audience :: Developers
Classifier: Intended Audience :: Information Technology
Classifier: Intended Audience :: System Administrators
Classifier: License :: OSI Approved :: GNU General Public License v2 or later (GPLv2+)
Classifier: Operating System :: MacOS :: MacOS X
Classifier: Operating System :: POSIX :: BSD :: FreeBSD
Classifier: Operating System :: POSIX :: Linux
Classifier: Programming Language :: Python
Classifier: Programming Language :: Python :: 3
Classifier: Programming Language :: Python :: 3.6
Classifier: Programming Language :: Python :: 3.7
Classifier: Programming Language :: Python :: 3.8
Classifier: Programming Language :: Python :: 3.9
Classifier: Programming Language :: Python :: 3.10
Classifier: Programming Language :: Python :: 3.11
Classifier: Topic :: Software Development :: Build Tools
Classifier: Topic :: System :: Archiving :: Packaging
License-File: COPYING
License-File: AUTHORS
Requires-Dist: cryptography
Requires-Dist: rpm
Requires-Dist: ruamel.yaml
Requires-Dist: urllib3
Provides-Extra: lint
Requires-Dist: darker==1.5.1; extra == "lint"
Requires-Dist: mypy; extra == "lint"
Dynamic: download-url
Dynamic: license-file
